gemini_tts/__init__.py
gemini_tts/tts.py
gemini_tts-0.1.2.dist-info/licenses/LICENSE
gemini_tts-0.1.2.dist-info/METADATA
gemini_tts-0.1.2.dist-info/WHEEL
gemini_tts-0.1.2.dist-info/top_level.txt
gemini_tts-0.1.2.dist-info/RECORD
