Metadata-Version: 2.4
Name: gemini-tts
Version: 0.1.2
Summary: A Python package for Gemini Text-to-Speech using the official API.
Author: Gemini TTS Developer
Author-email: David Suragan <dauitsuragan002@gmail.com>
License-Expression: MIT
Project-URL: Homepage, https://github.com/dauitsuragan002/gemini-tts
Project-URL: Bug Tracker, https://github.com/dauitsuragan002/gemini-tts/issues
Keywords: gemini,tts,text-to-speech,google,ai
Classifier: Development Status :: 3 - Alpha
Classifier: Intended Audience :: Developers
Classifier: Programming Language :: Python :: 3
Classifier: Programming Language :: Python :: 3.7
Classifier: Programming Language :: Python :: 3.8
Classifier: Programming Language :: Python :: 3.9
Classifier: Programming Language :: Python :: 3.10
Classifier: Programming Language :: Python :: 3.11
Classifier: Topic :: Multimedia :: Sound/Audio :: Speech
Classifier: Topic :: Scientific/Engineering :: Artificial Intelligence
Classifier: Topic :: Software Development :: Libraries :: Python Modules
Requires-Python: >=3.7
License-File: LICENSE
Requires-Dist: websockets>=12.0
Requires-Dist: wave>=0.0.2
Provides-Extra: audio
Requires-Dist: pygame>=2.0.0; extra == "audio"
Dynamic: author
Dynamic: license-file
Dynamic: requires-python
